<?xml version="1.0" encoding="UTF-8"?>
<!DOCTYPE mapper PUBLIC "-//mybatis.org//DTD Mapper 3.0//EN" "http://mybatis.org/dtd/mybatis-3-mapper.dtd">
<mapper namespace="com.eLearnPlayer.mapper.MedalInfoMapper">
  <resultMap id="BaseResultMap" type="com.eLearnPlayer.entity.MedalInfo">
    <!--
      WARNING - @mbg.generated
      This element is automatically generated by MyBatis Generator, do not modify.
    -->
    <id column="Medal_id" jdbcType="INTEGER" property="medalId" />
    <result column="Medal_name" jdbcType="VARCHAR" property="medalName" />
  </resultMap>
  <sql id="Base_Column_List">
    <!--
      WARNING - @mbg.generated
      This element is automatically generated by MyBatis Generator, do not modify.
    -->
    Medal_id, Medal_name
  </sql>
  <select id="getAll" resultType="com.eLearnPlayer.entity.MedalInfo">
    SELECT * FROM medal_info
  </select>

</mapper>